bomiot_token-0.7.0.dist-info/METADATA
bomiot_token-0.7.0.dist-info/WHEEL
bomiot_token-0.7.0.dist-info/licenses/LICENSE
bomiot_token/__init__.py
bomiot_token/bomiot_token.cp311-win_amd64.pyd
bomiot_token-0.7.0.dist-info/RECORD
