Metadata-Version: 2.4
Name: bomiot_token
Version: 0.7.0
Classifier: Programming Language :: Python
Classifier: Programming Language :: Python :: 3
Classifier: Programming Language :: Python :: 3.9
Classifier: Programming Language :: Python :: 3.10
Classifier: Programming Language :: Python :: 3.11
Classifier: Programming Language :: Python :: 3.12
Classifier: Programming Language :: Python :: 3.13
License-File: LICENSE
Summary: Bomiot Token validation
Keywords: Bomiot,bomiot
Author-email: Bomiot <Singosgu@gmail.com>
Requires-Python: >=3.9
